git_dag/__init__.py
git_dag/_version.py
git_dag/cli.py
git_dag/constants.py
git_dag/dag.py
git_dag/exceptions.py
git_dag/git_commands.py
git_dag/git_objects.py
git_dag/git_repository.py
git_dag/parameters.py
git_dag/py.typed
git_dag/utils.py
git_dag/interfaces/dag_base.py
git_dag/interfaces/graphviz.py
git_dag/test/conftest.py
git_dag/test/test_cli.py
git_dag/test/test_git_commands.py
git_dag/test/test_git_repository.py
git_dag/test/test_parameters.py
git_dag/test/test_real_repos.py
git_dag/test/test_utils.py
git_dag/test/resources/default_repo.gv
git_dag/test/resources/default_repo.repr
git_dag/test/resources/empty_repo_cluster.gv
git_dag-0.1.5.dist-info/licenses/LICENSE
git_dag-0.1.5.dist-info/METADATA
git_dag-0.1.5.dist-info/WHEEL
git_dag-0.1.5.dist-info/entry_points.txt
git_dag-0.1.5.dist-info/top_level.txt
git_dag-0.1.5.dist-info/RECORD
